Metadata-Version: 1.0
Name: distributions-file
Version: 2.0
Summary: Gaussian distributions
Home-page: UNKNOWN
Author: Sombit Bose
Author-email: bsombit@gmail.com
License: UNKNOWN
Platform: UNKNOWN
